AUTHORS
ChangeLog
Dockerfile
LICENSE.md
MANIFEST.in
Makefile
README.md
circle.yml
pytest.ini
setup.cfg
setup.py
tox.ini
build.d/20-salt-masterless
salt_layers/__init__.py
salt_layers.egg-info/PKG-INFO
salt_layers.egg-info/SOURCES.txt
salt_layers.egg-info/dependency_links.txt
salt_layers.egg-info/entry_points.txt
salt_layers.egg-info/not-zip-safe
salt_layers.egg-info/pbr.json
salt_layers.egg-info/requires.txt
salt_layers.egg-info/top_level.txt
salt_layers/apply/__init__.py
salt_layers/apply/__main__.py
tools/pip-requires